aiohttp_tools/__init__.py
aiohttp_tools/context_processors.py
aiohttp_tools/flash.py
aiohttp_tools/jinja.py
aiohttp_tools/middlewares.py
aiohttp_tools/static_url.py
aiohttp_tools-0.2.2.dist-info/LICENSE
aiohttp_tools-0.2.2.dist-info/METADATA
aiohttp_tools-0.2.2.dist-info/WHEEL
aiohttp_tools-0.2.2.dist-info/top_level.txt
aiohttp_tools-0.2.2.dist-info/RECORD
