Metadata-Version: 2.1
Name: aiohttp-tools
Version: 0.2.2
Summary: A set of little tools for aiohttp-based sites
Home-page: https://github.com/imbolc/aiohttp_tools
Author: Imbolc
Author-email: imbolc@imbolc.name
License: ISC
Platform: UNKNOWN
Classifier: License :: OSI Approved :: ISC License (ISCL)
Classifier: Intended Audience :: Developers
Classifier: Programming Language :: Python :: 3
